{
  "hash": "cccc05e7",
  "configHash": "1613719c",
  "lockfileHash": "6a46fb10",
  "browserHash": "66ed4c36",
  "optimized": {
    "react": {
      "src": "../../node_modules/react/index.js",
      "file": "react.js",
      "fileHash": "43084879",
      "needsInterop": true
    },
    "react-dom/client": {
      "src": "../../node_modules/react-dom/client.js",
      "file": "react-dom_client.js",
      "fileHash": "36ebe695",
      "needsInterop": true
    }
  },
  "chunks": {
    "chunk-Y455YYDO": {
      "file": "chunk-Y455YYDO.js"
    }
  }
}